{
    "fit_ok": true,
    "frac;766": 0.4365453831681347,
    "frac;766_err": 0.021650598026556608,
    "info_fit": "------------------------------------------------------------------\n| FCN = -3.199e+05              |     Ncalls=103 (103 total)     |\n| EDM = 0.000979 (Goal: 0.001)  |            up = 0.5            |\n------------------------------------------------------------------\n|  Valid Min.   | Valid Param.  | Above EDM | Reached call limit |\n------------------------------------------------------------------\n|     True      |     True      |   False   |       False        |\n------------------------------------------------------------------\n| Hesse failed  |   Has cov.    | Accurate  | Pos. def. | Forced |\n------------------------------------------------------------------\n|     False     |     True      |   True    |   True    | False  |\n------------------------------------------------------------------",
    "info_params": "name            value    minuit_hesse    at limit\n----------  ---------  --------------  ----------\nn_sig;766       52130     +/- 2.8e+02       False\u001b[0m\nn_bkg;766        5201     +/- 1.8e+02       False\u001b[0m\nfrac;766       0.4365     +/-   0.022       False\u001b[0m\nmu;766           5279     +/-   0.078       False\u001b[0m\nsigmaL;766      11.05     +/-    0.22       False\u001b[0m\nsigmaR;766      18.16     +/-    0.23       False\u001b[0m\nlambda;766  -0.002156     +/- 0.00026       False\u001b[0m",
    "lambda;766": -0.0021557604906720096,
    "lambda;766_err": 0.0002571186991522826,
    "mu;766": 5278.864820691623,
    "mu;766_err": 0.07753950582413811,
    "n_bkg;766": 5201.118662408354,
    "n_bkg;766_err": 180.7853217116717,
    "n_sig;766": 52127.31368393184,
    "n_sig;766_err": 278.1764168785167,
    "r_params": {
        "alphaL": 2.013056405264425,
        "alphaL_Kpipi": 0.23984147888569726,
        "alphaR": -1.7373659042137568,
        "alphaR_Kpipi": -3.45169511727099,
        "fraction_Kpipi": 0.8861855867303668,
        "muL_Kpipi": 5214.656416664541,
        "muR_Kpipi": 5183.074248990296,
        "nL": 0.48683546107887377,
        "nL_Kpipi": 4.413073505098077,
        "nR": 7.51571970417884,
        "nR_Kpipi": 1.3686501931786665e-08,
        "r_bkgK": 0.035341458516519916,
        "sigmaL_Kpipi": 19.133710600596434,
        "sigmaR_Kpipi": 39.32384704379869
    },
    "sigmaL;766": 11.045044567037621,
    "sigmaL;766_err": 0.21727446228794947,
    "sigmaR;766": 18.15985034537977,
    "sigmaR;766_err": 0.2347413977415701
}