{
    "fit_ok": true,
    "frac;32": 0.31362209246854544,
    "frac;32_err": 0.015511036494001804,
    "info_fit": "------------------------------------------------------------------\n| FCN = -3.199e+05              |     Ncalls=103 (103 total)     |\n| EDM = 2.08e-05 (Goal: 0.001)  |            up = 0.5            |\n------------------------------------------------------------------\n|  Valid Min.   | Valid Param.  | Above EDM | Reached call limit |\n------------------------------------------------------------------\n|     True      |     True      |   False   |       False        |\n------------------------------------------------------------------\n| Hesse failed  |   Has cov.    | Accurate  | Pos. def. | Forced |\n------------------------------------------------------------------\n|     False     |     True      |   True    |   True    | False  |\n------------------------------------------------------------------",
    "info_params": "name           value    minuit_hesse    at limit\n---------  ---------  --------------  ----------\nn_sig;32       52580     +/- 2.8e+02       False\u001b[0m\nn_bkg;32        4731     +/- 1.8e+02       False\u001b[0m\nfrac;32       0.3136     +/-   0.016       False\u001b[0m\nmu;32           5279     +/-   0.078       False\u001b[0m\nsigmaL;32      9.955     +/-    0.27       False\u001b[0m\nsigmaR;32      17.16     +/-    0.15       False\u001b[0m\nlambda;32  -0.001366     +/- 0.00029       False\u001b[0m",
    "lambda;32": -0.0013655735546230507,
    "lambda;32_err": 0.0002940104979937999,
    "mu;32": 5278.869664926247,
    "mu;32_err": 0.07832967465661092,
    "n_bkg;32": 4731.107534377146,
    "n_bkg;32_err": 179.80945713854516,
    "n_sig;32": 52581.32377113373,
    "n_sig;32_err": 279.0589217922932,
    "r_params": {
        "alphaL": 2.014363397174307,
        "alphaL_Kpipi": 0.23984147888569726,
        "alphaR": -1.7688921531162682,
        "alphaR_Kpipi": -3.45169511727099,
        "fraction_Kpipi": 0.8861855867303668,
        "muL_Kpipi": 5214.656416664541,
        "muR_Kpipi": 5183.074248990296,
        "nL": 0.2660825520968781,
        "nL_Kpipi": 4.413073505098077,
        "nR": 7.502295835171705,
        "nR_Kpipi": 1.3686501931786665e-08,
        "r_bkgK": 0.035341458516519916,
        "sigmaL_Kpipi": 19.133710600596434,
        "sigmaR_Kpipi": 39.32384704379869
    },
    "sigmaL;32": 9.954696322256135,
    "sigmaL;32_err": 0.2696421572984572,
    "sigmaR;32": 17.161240297512407,
    "sigmaR;32_err": 0.14851035637772886
}