{
    "fit_ok": true,
    "frac;446": 0.48035485110600235,
    "frac;446_err": 0.02115234581635538,
    "info_fit": "------------------------------------------------------------------\n| FCN = -3.199e+05              |     Ncalls=103 (103 total)     |\n| EDM = 5.09e-05 (Goal: 0.001)  |            up = 0.5            |\n------------------------------------------------------------------\n|  Valid Min.   | Valid Param.  | Above EDM | Reached call limit |\n------------------------------------------------------------------\n|     True      |     True      |   False   |       False        |\n------------------------------------------------------------------\n| Hesse failed  |   Has cov.    | Accurate  | Pos. def. | Forced |\n------------------------------------------------------------------\n|     False     |     True      |   True    |   True    | False  |\n------------------------------------------------------------------",
    "info_params": "name            value    minuit_hesse    at limit\n----------  ---------  --------------  ----------\nn_sig;446       52520     +/- 2.8e+02       False\u001b[0m\nn_bkg;446        5297     +/- 1.9e+02       False\u001b[0m\nfrac;446       0.4804     +/-   0.021       False\u001b[0m\nmu;446           5279     +/-   0.077       False\u001b[0m\nsigmaL;446      11.33     +/-     0.2       False\u001b[0m\nsigmaR;446      18.53     +/-    0.26       False\u001b[0m\nlambda;446  -0.002351     +/- 0.00026       False\u001b[0m",
    "lambda;446": -0.002350587882191557,
    "lambda;446_err": 0.0002562260835554416,
    "mu;446": 5278.87211667735,
    "mu;446_err": 0.0772750734084534,
    "n_bkg;446": 5296.700414075536,
    "n_bkg;446_err": 185.22072722860725,
    "n_sig;446": 52524.37947959964,
    "n_sig;446_err": 283.23086377243726,
    "r_params": {
        "alphaL": 2.02992217591786,
        "alphaL_Kpipi": 0.22486504926108575,
        "alphaR": -1.7778067363088699,
        "alphaR_Kpipi": -3.238717119045423,
        "fraction_Kpipi": 0.8993052188310624,
        "muL_Kpipi": 5214.945930664334,
        "muR_Kpipi": 5186.0957377842215,
        "nL": 0.4354740104546931,
        "nL_Kpipi": 4.502671498885786,
        "nR": 5.840596424652496,
        "nR_Kpipi": 0.0002965106907779028,
        "r_bkgK": 0.02575650218839202,
        "sigmaL_Kpipi": 19.078376588403554,
        "sigmaR_Kpipi": 37.888513882621965
    },
    "sigmaL;446": 11.332791416806437,
    "sigmaL;446_err": 0.19908409944242839,
    "sigmaR;446": 18.534893844440354,
    "sigmaR;446_err": 0.2566776366581665
}