{
    "fit_ok": true,
    "frac;1270": 0.5407800841436757,
    "frac;1270_err": 0.02392416938743809,
    "info_fit": "------------------------------------------------------------------\n| FCN = -3.199e+05              |     Ncalls=106 (106 total)     |\n| EDM = 8.46e-06 (Goal: 0.001)  |            up = 0.5            |\n------------------------------------------------------------------\n|  Valid Min.   | Valid Param.  | Above EDM | Reached call limit |\n------------------------------------------------------------------\n|     True      |     True      |   False   |       False        |\n------------------------------------------------------------------\n| Hesse failed  |   Has cov.    | Accurate  | Pos. def. | Forced |\n------------------------------------------------------------------\n|     False     |     True      |   True    |   True    | False  |\n------------------------------------------------------------------",
    "info_params": "name             value    minuit_hesse    at limit\n-----------  ---------  --------------  ----------\nn_sig;1270       51950     +/- 2.7e+02       False\u001b[0m\nn_bkg;1270        5384     +/- 1.7e+02       False\u001b[0m\nfrac;1270       0.5408     +/-   0.024       False\u001b[0m\nmu;1270           5279     +/-   0.077       False\u001b[0m\nsigmaL;1270       11.8     +/-    0.19       False\u001b[0m\nsigmaR;1270      19.28     +/-    0.33       False\u001b[0m\nlambda;1270  -0.002645     +/- 0.00022       False\u001b[0m",
    "lambda;1270": -0.0026453093545860673,
    "lambda;1270_err": 0.00022305535664203066,
    "mu;1270": 5278.823691820202,
    "mu;1270_err": 0.07683232953940146,
    "n_bkg;1270": 5384.371288797134,
    "n_bkg;1270_err": 165.5109537532524,
    "n_sig;1270": 51954.091836760024,
    "n_sig;1270_err": 268.6672957015835,
    "r_params": {
        "alphaL": 2.090456174111837,
        "alphaL_Kpipi": 0.23984147888569726,
        "alphaR": -1.7371288315153974,
        "alphaR_Kpipi": -3.45169511727099,
        "fraction_Kpipi": 0.8861855867303668,
        "muL_Kpipi": 5214.656416664541,
        "muR_Kpipi": 5183.074248990296,
        "nL": 0.5919160385589839,
        "nL_Kpipi": 4.413073505098077,
        "nR": 4.77717823315516,
        "nR_Kpipi": 1.3686501931786665e-08,
        "r_bkgK": 0.035341458516519916,
        "sigmaL_Kpipi": 19.133710600596434,
        "sigmaR_Kpipi": 39.32384704379869
    },
    "sigmaL;1270": 11.804724230712857,
    "sigmaL;1270_err": 0.1926995870659822,
    "sigmaR;1270": 19.278970188983774,
    "sigmaR;1270_err": 0.33141759755447187
}