{
    "fit_ok": true,
    "frac;841": 0.4789556595434593,
    "frac;841_err": 0.021314602199347492,
    "info_fit": "------------------------------------------------------------------\n| FCN = -3.199e+05              |     Ncalls=101 (101 total)     |\n| EDM = 0.000103 (Goal: 0.001)  |            up = 0.5            |\n------------------------------------------------------------------\n|  Valid Min.   | Valid Param.  | Above EDM | Reached call limit |\n------------------------------------------------------------------\n|     True      |     True      |   False   |       False        |\n------------------------------------------------------------------\n| Hesse failed  |   Has cov.    | Accurate  | Pos. def. | Forced |\n------------------------------------------------------------------\n|     False     |     True      |   True    |   True    | False  |\n------------------------------------------------------------------",
    "info_params": "name            value    minuit_hesse    at limit\n----------  ---------  --------------  ----------\nn_sig;841       52480     +/- 2.8e+02       False\u001b[0m\nn_bkg;841        5333     +/- 1.9e+02       False\u001b[0m\nfrac;841        0.479     +/-   0.021       False\u001b[0m\nmu;841           5279     +/-   0.077       False\u001b[0m\nsigmaL;841      11.33     +/-     0.2       False\u001b[0m\nsigmaR;841      18.49     +/-    0.26       False\u001b[0m\nlambda;841  -0.002395     +/- 0.00025       False\u001b[0m",
    "lambda;841": -0.002394744884557487,
    "lambda;841_err": 0.00025490414940071876,
    "mu;841": 5278.878457913067,
    "mu;841_err": 0.07728591942006552,
    "n_bkg;841": 5333.037566249332,
    "n_bkg;841_err": 185.79963720894796,
    "n_sig;841": 52484.00241148789,
    "n_sig;841_err": 283.44112698411334,
    "r_params": {
        "alphaL": 2.02992217591786,
        "alphaL_Kpipi": 0.25051560673742396,
        "alphaR": -1.7778067363088699,
        "alphaR_Kpipi": -3.4799350936953783,
        "fraction_Kpipi": 0.8964038695013775,
        "muL_Kpipi": 5214.916904725329,
        "muR_Kpipi": 5184.2332358873355,
        "nL": 0.4354740104546931,
        "nL_Kpipi": 4.509362277767327,
        "nR": 5.840596424652496,
        "nR_Kpipi": 2.9725676142082233e-06,
        "r_bkgK": 0.025856046172420277,
        "sigmaL_Kpipi": 19.989476959309954,
        "sigmaR_Kpipi": 39.73388377179209
    },
    "sigmaL;841": 11.329005679775587,
    "sigmaL;841_err": 0.20050481750192334,
    "sigmaR;841": 18.492706629140997,
    "sigmaR;841_err": 0.25625257483155717
}