{
    "fit_ok": true,
    "frac;84": 0.3254127585961819,
    "frac;84_err": 0.018222726226570004,
    "info_fit": "------------------------------------------------------------------\n| FCN = -3.199e+05              |     Ncalls=106 (106 total)     |\n| EDM = 0.000197 (Goal: 0.001)  |            up = 0.5            |\n------------------------------------------------------------------\n|  Valid Min.   | Valid Param.  | Above EDM | Reached call limit |\n------------------------------------------------------------------\n|     True      |     True      |   False   |       False        |\n------------------------------------------------------------------\n| Hesse failed  |   Has cov.    | Accurate  | Pos. def. | Forced |\n------------------------------------------------------------------\n|     False     |     True      |   True    |   True    | False  |\n------------------------------------------------------------------",
    "info_params": "name           value    minuit_hesse    at limit\n---------  ---------  --------------  ----------\nn_sig;84       51920     +/- 2.7e+02       False\u001b[0m\nn_bkg;84        4499     +/- 1.6e+02       False\u001b[0m\nfrac;84       0.3254     +/-   0.018       False\u001b[0m\nmu;84           5279     +/-   0.078       False\u001b[0m\nsigmaL;84      10.12     +/-    0.24       False\u001b[0m\nsigmaR;84      17.46     +/-    0.17       False\u001b[0m\nlambda;84  -0.001127     +/- 0.00029       False\u001b[0m",
    "lambda;84": -0.001126812535287347,
    "lambda;84_err": 0.0002857682195546935,
    "mu;84": 5278.829542242209,
    "mu;84_err": 0.07780434717222623,
    "n_bkg;84": 4499.442164613987,
    "n_bkg;84_err": 164.77947182051557,
    "n_sig;84": 51917.41985616609,
    "n_sig;84_err": 266.6257202132067,
    "r_params": {
        "alphaL": 2.02992217591786,
        "alphaL_Kpipi": 0.2605291883457314,
        "alphaR": -1.7778067363088699,
        "alphaR_Kpipi": -3.3729763204865364,
        "fraction_Kpipi": 0.9081775569880197,
        "muL_Kpipi": 5213.168760643046,
        "muR_Kpipi": 5184.078483535328,
        "nL": 0.4354740104546931,
        "nL_Kpipi": 4.4900615167257705,
        "nR": 5.840596424652496,
        "nR_Kpipi": 5.4472415972687654e-05,
        "r_bkgK": 0.053021316575516446,
        "sigmaL_Kpipi": 18.686194925965815,
        "sigmaR_Kpipi": 42.01332839240646
    },
    "sigmaL;84": 10.122389192028066,
    "sigmaL;84_err": 0.24454084952940805,
    "sigmaR;84": 17.45554638807798,
    "sigmaR;84_err": 0.17493177755268588
}