{
    "fit_ok": true,
    "frac;172": 0.4263081275490735,
    "frac;172_err": 0.020508759067030286,
    "info_fit": "------------------------------------------------------------------\n| FCN = -3.199e+05              |     Ncalls=104 (104 total)     |\n| EDM = 0.000406 (Goal: 0.001)  |            up = 0.5            |\n------------------------------------------------------------------\n|  Valid Min.   | Valid Param.  | Above EDM | Reached call limit |\n------------------------------------------------------------------\n|     True      |     True      |   False   |       False        |\n------------------------------------------------------------------\n| Hesse failed  |   Has cov.    | Accurate  | Pos. def. | Forced |\n------------------------------------------------------------------\n|     False     |     True      |   True    |   True    | False  |\n------------------------------------------------------------------",
    "info_params": "name            value    minuit_hesse    at limit\n----------  ---------  --------------  ----------\nn_sig;172       52390     +/- 2.8e+02       False\u001b[0m\nn_bkg;172        4997     +/- 1.8e+02       False\u001b[0m\nfrac;172       0.4263     +/-   0.021       False\u001b[0m\nmu;172           5279     +/-   0.077       False\u001b[0m\nsigmaL;172      10.93     +/-    0.22       False\u001b[0m\nsigmaR;172      18.09     +/-    0.22       False\u001b[0m\nlambda;172  -0.001922     +/- 0.00027       False\u001b[0m",
    "lambda;172": -0.0019221382994113467,
    "lambda;172_err": 0.0002703071296325579,
    "mu;172": 5278.861193616084,
    "mu;172_err": 0.07726863225611953,
    "n_bkg;172": 4997.200726763073,
    "n_bkg;172_err": 180.293382081351,
    "n_sig;172": 52389.52382818622,
    "n_sig;172_err": 278.5807966846786,
    "r_params": {
        "alphaL": 2.02992217591786,
        "alphaL_Kpipi": 0.23984147888569726,
        "alphaR": -1.7778067363088699,
        "alphaR_Kpipi": -3.45169511727099,
        "fraction_Kpipi": 0.8861855867303668,
        "muL_Kpipi": 5214.656416664541,
        "muR_Kpipi": 5183.074248990296,
        "mu_Ds": 5279.562650425372,
        "nL": 0.4354740104546931,
        "nL_Kpipi": 4.413073505098077,
        "nR": 5.840596424652496,
        "nR_Kpipi": 1.3686501931786665e-08,
        "n_sig_Ds": 1316.4389451944553,
        "r_bkgK": 0.035341458516519916,
        "sigmaL_Kpipi": 19.133710600596434,
        "sigmaR_Kpipi": 39.32384704379869,
        "sigma_Ds": 12.996546527257522
    },
    "sigmaL;172": 10.92854254095182,
    "sigmaL;172_err": 0.21739916301919868,
    "sigmaR;172": 18.093243387736575,
    "sigmaR;172_err": 0.2228316110873818
}