{
    "fit_ok": false,
    "frac;914": 0.4263267290950458,
    "frac;914_err": 0.020592999576458257,
    "info_fit": "------------------------------------------------------------------\n| FCN = -3.199e+05              |     Ncalls=101 (101 total)     |\n| EDM = 0.00121 (Goal: 0.001)   |            up = 0.5            |\n------------------------------------------------------------------\n|  Valid Min.   | Valid Param.  | Above EDM | Reached call limit |\n------------------------------------------------------------------\n|     True      |     True      |   False   |       False        |\n------------------------------------------------------------------\n| Hesse failed  |   Has cov.    | Accurate  | Pos. def. | Forced |\n------------------------------------------------------------------\n|     False     |     True      |   True    |   True    | False  |\n------------------------------------------------------------------",
    "info_params": "name            value    minuit_hesse    at limit\n----------  ---------  --------------  ----------\nn_sig;914       52330     +/- 2.8e+02       False\u001b[0m\nn_bkg;914        5002     +/- 1.8e+02       False\u001b[0m\nfrac;914       0.4263     +/-   0.021       False\u001b[0m\nmu;914           5279     +/-   0.077       False\u001b[0m\nsigmaL;914      10.95     +/-    0.22       False\u001b[0m\nsigmaR;914      18.12     +/-    0.22       False\u001b[0m\nlambda;914  -0.001933     +/- 0.00027       False\u001b[0m",
    "lambda;914": -0.0019334038697048639,
    "lambda;914_err": 0.0002703710319225486,
    "mu;914": 5278.8929672163995,
    "mu;914_err": 0.07747145075824716,
    "n_bkg;914": 5002.367460969401,
    "n_bkg;914_err": 180.63446347655534,
    "n_sig;914": 52327.48840431629,
    "n_sig;914_err": 278.7514919102341,
    "r_params": {
        "alphaL": 2.02992217591786,
        "alphaL_Kpipi": 0.23984147888569726,
        "alphaR": -1.7778067363088699,
        "alphaR_Kpipi": -3.45169511727099,
        "fraction_Kpipi": 0.8861855867303668,
        "muL_Kpipi": 5214.656416664541,
        "muR_Kpipi": 5183.074248990296,
        "mu_Ds": 5278.470653090651,
        "nL": 0.4354740104546931,
        "nL_Kpipi": 4.413073505098077,
        "nR": 5.840596424652496,
        "nR_Kpipi": 1.3686501931786665e-08,
        "n_sig_Ds": 1375.741969268903,
        "r_bkgK": 0.035341458516519916,
        "sigmaL_Kpipi": 19.133710600596434,
        "sigmaR_Kpipi": 39.32384704379869,
        "sigma_Ds": 12.373571162894939
    },
    "sigmaL;914": 10.952443196163584,
    "sigmaL;914_err": 0.2181292524993931,
    "sigmaR;914": 18.11713937773142,
    "sigmaR;914_err": 0.22360801079818177
}