{
    "fit_ok": true,
    "frac;689": 0.2980613712832693,
    "frac;689_err": 0.011433112486296847,
    "info_fit": "------------------------------------------------------------------\n| FCN = -3.172e+05              |      Ncalls=94 (94 total)      |\n| EDM = 0.000243 (Goal: 0.001)  |            up = 0.5            |\n------------------------------------------------------------------\n|  Valid Min.   | Valid Param.  | Above EDM | Reached call limit |\n------------------------------------------------------------------\n|     True      |     True      |   False   |       False        |\n------------------------------------------------------------------\n| Hesse failed  |   Has cov.    | Accurate  | Pos. def. | Forced |\n------------------------------------------------------------------\n|     False     |     True      |   True    |   True    | False  |\n------------------------------------------------------------------",
    "info_params": "name             value    minuit_hesse    at limit\n----------  ----------  --------------  ----------\nn_sig;689        52400     +/- 2.6e+02       False\u001b[0m\nn_bkg;689         5137     +/- 1.4e+02       False\u001b[0m\nfrac;689        0.2981     +/-   0.011       False\u001b[0m\nmu;689            5279     +/-    0.08       False\u001b[0m\nsigmaL;689       9.957     +/-    0.29       False\u001b[0m\nsigmaR;689       16.79     +/-    0.12       False\u001b[0m\nlambda;689  -9.227e-05     +/- 0.00022       False\u001b[0m",
    "lambda;689": -9.226716393520573e-05,
    "lambda;689_err": 0.00022137573374320812,
    "mu;689": 5278.817885217798,
    "mu;689_err": 0.08001191500239438,
    "n_bkg;689": 5137.3728585718445,
    "n_bkg;689_err": 139.23708135824572,
    "n_sig;689": 52399.850695449306,
    "n_sig;689_err": 255.07069671755553,
    "r_params": {
        "alphaL": 2.001508780521077,
        "alphaL_Kpipi": 0.23984147888569726,
        "alphaR": -1.6123957888005773,
        "alphaR_Kpipi": -3.45169511727099,
        "fraction_Kpipi": 0.8861855867303668,
        "muL_Kpipi": 5214.656416664541,
        "muR_Kpipi": 5183.074248990296,
        "nL": 0.1849554195154191,
        "nL_Kpipi": 4.413073505098077,
        "nR": 6.822409716187387,
        "nR_Kpipi": 1.3686501931786665e-08,
        "r_bkgK": 0.03478781022148211,
        "sigmaL_Kpipi": 19.133710600596434,
        "sigmaR_Kpipi": 39.32384704379869
    },
    "sigmaL;689": 9.957377591780148,
    "sigmaL;689_err": 0.29382202848668726,
    "sigmaR;689": 16.78515902655718,
    "sigmaR;689_err": 0.11561349394802585
}