{
    "fit_ok": true,
    "frac;871": 0.4309671399516337,
    "frac;871_err": 0.015461525203126516,
    "info_fit": "------------------------------------------------------------------\n| FCN = -3.172e+05              |     Ncalls=104 (104 total)     |\n| EDM = 7.66e-05 (Goal: 0.001)  |            up = 0.5            |\n------------------------------------------------------------------\n|  Valid Min.   | Valid Param.  | Above EDM | Reached call limit |\n------------------------------------------------------------------\n|     True      |     True      |   False   |       False        |\n------------------------------------------------------------------\n| Hesse failed  |   Has cov.    | Accurate  | Pos. def. | Forced |\n------------------------------------------------------------------\n|     False     |     True      |   True    |   True    | False  |\n------------------------------------------------------------------",
    "info_params": "name             value    minuit_hesse    at limit\n----------  ----------  --------------  ----------\nn_sig;871        52550     +/- 2.7e+02       False\u001b[0m\nn_bkg;871         4984     +/- 1.7e+02       False\u001b[0m\nfrac;871         0.431     +/-   0.015       False\u001b[0m\nmu;871            5279     +/-   0.079       False\u001b[0m\nsigmaL;871       11.01     +/-     0.2       False\u001b[0m\nsigmaR;871       18.07     +/-    0.19       False\u001b[0m\nlambda;871  -0.0005537     +/- 0.00028       False\u001b[0m",
    "lambda;871": -0.0005536547369580369,
    "lambda;871_err": 0.0002820262212086518,
    "mu;871": 5278.94276574951,
    "mu;871_err": 0.0786833398309883,
    "n_bkg;871": 4983.765265914268,
    "n_bkg;871_err": 171.24993962302037,
    "n_sig;871": 52550.44383585444,
    "n_sig;871_err": 273.6569513611602,
    "r_params": {
        "alphaL": 1.93986625640777,
        "alphaL_Kpipi": 0.23984147888569726,
        "alphaR": -1.865629201074866,
        "alphaR_Kpipi": -3.45169511727099,
        "fraction_Kpipi": 0.8861855867303668,
        "muL_Kpipi": 5214.656416664541,
        "muR_Kpipi": 5183.074248990296,
        "nL": 0.41671713226485096,
        "nL_Kpipi": 4.413073505098077,
        "nR": 2.4138996982596224,
        "nR_Kpipi": 1.3686501931786665e-08,
        "r_bkgK": 0.03478781022148211,
        "sigmaL_Kpipi": 19.133710600596434,
        "sigmaR_Kpipi": 39.32384704379869
    },
    "sigmaL;871": 11.01021986343394,
    "sigmaL;871_err": 0.1979819388591729,
    "sigmaR;871": 18.07398341605141,
    "sigmaR;871_err": 0.19346731306930343
}