{
    "fit_ok": true,
    "frac;32": 0.38516222280918244,
    "frac;32_err": 0.019286158369059742,
    "info_fit": "------------------------------------------------------------------\n| FCN = -3.172e+05              |     Ncalls=105 (105 total)     |\n| EDM = 5.16e-05 (Goal: 0.001)  |            up = 0.5            |\n------------------------------------------------------------------\n|  Valid Min.   | Valid Param.  | Above EDM | Reached call limit |\n------------------------------------------------------------------\n|     True      |     True      |   False   |       False        |\n------------------------------------------------------------------\n| Hesse failed  |   Has cov.    | Accurate  | Pos. def. | Forced |\n------------------------------------------------------------------\n|     False     |     True      |   True    |   True    | False  |\n------------------------------------------------------------------",
    "info_params": "name           value    minuit_hesse    at limit\n---------  ---------  --------------  ----------\nn_sig;32       51420     +/- 2.8e+02       False\u001b[0m\nn_bkg;32        6150     +/- 1.9e+02       False\u001b[0m\nfrac;32       0.3852     +/-   0.019       False\u001b[0m\nmu;32           5279     +/-   0.079       False\u001b[0m\nsigmaL;32      10.57     +/-    0.23       False\u001b[0m\nsigmaR;32       17.8     +/-     0.2       False\u001b[0m\nlambda;32  -0.001417     +/- 0.00024       False\u001b[0m",
    "lambda;32": -0.0014166207484944265,
    "lambda;32_err": 0.00024421950659704524,
    "mu;32": 5278.881888493204,
    "mu;32_err": 0.07868334337922794,
    "n_bkg;32": 6150.07597147655,
    "n_bkg;32_err": 193.7788021385495,
    "n_sig;32": 51423.50216692913,
    "n_sig;32_err": 283.42606009351726,
    "r_params": {
        "alphaL": 2.0277392296920453,
        "alphaL_Kpipi": 0.23984147888569726,
        "alphaR": -1.7648560591191302,
        "alphaR_Kpipi": -3.45169511727099,
        "fraction_Kpipi": 0.8861855867303668,
        "muL_Kpipi": 5214.656416664541,
        "muR_Kpipi": 5183.074248990296,
        "nL": 0.36843582314168966,
        "nL_Kpipi": 4.413073505098077,
        "nR": 7.415828349898629,
        "nR_Kpipi": 1.3686501931786665e-08,
        "r_bkgK": 0.03478781022148211,
        "sigmaL_Kpipi": 19.133710600596434,
        "sigmaR_Kpipi": 39.32384704379869
    },
    "sigmaL;32": 10.573276862025065,
    "sigmaL;32_err": 0.22505882898325275,
    "sigmaR;32": 17.79697584455853,
    "sigmaR;32_err": 0.20372112488237656
}