{
    "fit_ok": true,
    "frac;594": 0.31738563317119106,
    "frac;594_err": 0.019094721697215513,
    "info_fit": "------------------------------------------------------------------\n| FCN = -3.172e+05              |     Ncalls=103 (103 total)     |\n| EDM = 8.34e-05 (Goal: 0.001)  |            up = 0.5            |\n------------------------------------------------------------------\n|  Valid Min.   | Valid Param.  | Above EDM | Reached call limit |\n------------------------------------------------------------------\n|     True      |     True      |   False   |       False        |\n------------------------------------------------------------------\n| Hesse failed  |   Has cov.    | Accurate  | Pos. def. | Forced |\n------------------------------------------------------------------\n|     False     |     True      |   True    |   True    | False  |\n------------------------------------------------------------------",
    "info_params": "name            value    minuit_hesse    at limit\n----------  ---------  --------------  ----------\nn_sig;594       50890     +/- 2.7e+02       False\u001b[0m\nn_bkg;594        5639     +/- 1.8e+02       False\u001b[0m\nfrac;594       0.3174     +/-   0.019       False\u001b[0m\nmu;594           5279     +/-   0.079       False\u001b[0m\nsigmaL;594      10.06     +/-    0.26       False\u001b[0m\nsigmaR;594      17.36     +/-    0.18       False\u001b[0m\nlambda;594  -0.000824     +/- 0.00025       False\u001b[0m",
    "lambda;594": -0.0008239913910169233,
    "lambda;594_err": 0.00024920494096715163,
    "mu;594": 5278.85607924813,
    "mu;594_err": 0.0788580746095736,
    "n_bkg;594": 5638.595975800084,
    "n_bkg;594_err": 175.42128556427852,
    "n_sig;594": 50893.5252340657,
    "n_sig;594_err": 268.414982090941,
    "r_params": {
        "alphaL": 2.030074578321816,
        "alphaL_Kpipi": 0.24707742652565945,
        "alphaR": -1.7613550245501948,
        "alphaR_Kpipi": -3.446613550243085,
        "fraction_Kpipi": 0.8841560133186548,
        "muL_Kpipi": 5215.404607681317,
        "muR_Kpipi": 5181.2020816610375,
        "nL": 0.4392329990731146,
        "nL_Kpipi": 4.1095285977446405,
        "nR": 5.840596424652496,
        "nR_Kpipi": 0.00011413451697153987,
        "r_bkgK": 0.05558231841692936,
        "sigmaL_Kpipi": 18.932470790020048,
        "sigmaR_Kpipi": 40.017574881514875
    },
    "sigmaL;594": 10.057766772974002,
    "sigmaL;594_err": 0.2590807392357297,
    "sigmaR;594": 17.358360654853776,
    "sigmaR;594_err": 0.18043832742610316
}