{
    "fit_ok": true,
    "frac;1221": 0.46754947036104433,
    "frac;1221_err": 0.022149423816031376,
    "info_fit": "------------------------------------------------------------------\n| FCN = -3.172e+05              |     Ncalls=105 (105 total)     |\n| EDM = 1.82e-05 (Goal: 0.001)  |            up = 0.5            |\n------------------------------------------------------------------\n|  Valid Min.   | Valid Param.  | Above EDM | Reached call limit |\n------------------------------------------------------------------\n|     True      |     True      |   False   |       False        |\n------------------------------------------------------------------\n| Hesse failed  |   Has cov.    | Accurate  | Pos. def. | Forced |\n------------------------------------------------------------------\n|     False     |     True      |   True    |   True    | False  |\n------------------------------------------------------------------",
    "info_params": "name             value    minuit_hesse    at limit\n-----------  ---------  --------------  ----------\nn_sig;1221       51430     +/- 2.8e+02       False\u001b[0m\nn_bkg;1221        6506     +/- 1.9e+02       False\u001b[0m\nfrac;1221       0.4675     +/-   0.022       False\u001b[0m\nmu;1221           5279     +/-   0.078       False\u001b[0m\nsigmaL;1221      11.25     +/-    0.21       False\u001b[0m\nsigmaR;1221      18.42     +/-    0.26       False\u001b[0m\nlambda;1221  -0.001941     +/- 0.00023       False\u001b[0m",
    "lambda;1221": -0.0019409263034287222,
    "lambda;1221_err": 0.00022532830061874516,
    "mu;1221": 5278.873990591083,
    "mu;1221_err": 0.07842027141401635,
    "n_bkg;1221": 6505.588302934864,
    "n_bkg;1221_err": 193.89420702678953,
    "n_sig;1221": 51426.431568633714,
    "n_sig;1221_err": 284.43675942858346,
    "r_params": {
        "alphaL": 2.032652256499463,
        "alphaL_Kpipi": 0.26424248526533994,
        "alphaR": -1.7656247571047547,
        "alphaR_Kpipi": -3.416779961503523,
        "fraction_Kpipi": 0.912442878806907,
        "muL_Kpipi": 5215.445348820311,
        "muR_Kpipi": 5184.422496802233,
        "nL": 0.4368034417751325,
        "nL_Kpipi": 4.246513567238376,
        "nR": 5.840596424652496,
        "nR_Kpipi": 0.0003814135148656682,
        "r_bkgK": 0.027328522994436045,
        "sigmaL_Kpipi": 18.010957520044357,
        "sigmaR_Kpipi": 38.715271948653026
    },
    "sigmaL;1221": 11.251124909815548,
    "sigmaL;1221_err": 0.21295974207299623,
    "sigmaR;1221": 18.42457467172912,
    "sigmaR;1221_err": 0.2588399709901791
}