{
    "fit_ok": true,
    "frac;1330": 0.5296413300658895,
    "frac;1330_err": 0.020834610485806152,
    "info_fit": "------------------------------------------------------------------\n| FCN = -3.172e+05              |     Ncalls=103 (103 total)     |\n| EDM = 5.52e-05 (Goal: 0.001)  |            up = 0.5            |\n------------------------------------------------------------------\n|  Valid Min.   | Valid Param.  | Above EDM | Reached call limit |\n------------------------------------------------------------------\n|     True      |     True      |   False   |       False        |\n------------------------------------------------------------------\n| Hesse failed  |   Has cov.    | Accurate  | Pos. def. | Forced |\n------------------------------------------------------------------\n|     False     |     True      |   True    |   True    | False  |\n------------------------------------------------------------------",
    "info_params": "name             value    minuit_hesse    at limit\n-----------  ---------  --------------  ----------\nn_sig;1330       51710     +/- 2.7e+02       False\u001b[0m\nn_bkg;1330        5833     +/- 1.7e+02       False\u001b[0m\nfrac;1330       0.5296     +/-   0.021       False\u001b[0m\nmu;1330           5279     +/-   0.078       False\u001b[0m\nsigmaL;1330      11.74     +/-    0.19       False\u001b[0m\nsigmaR;1330      19.06     +/-    0.29       False\u001b[0m\nlambda;1330  -0.001859     +/- 0.00023       False\u001b[0m",
    "lambda;1330": -0.0018593795474202285,
    "lambda;1330_err": 0.00022975916107411952,
    "mu;1330": 5278.932632330466,
    "mu;1330_err": 0.07835123546343556,
    "n_bkg;1330": 5832.508859561328,
    "n_bkg;1330_err": 168.6498017983685,
    "n_sig;1330": 51707.227187258075,
    "n_sig;1330_err": 269.3140636210153,
    "r_params": {
        "alphaL": 1.941312978675727,
        "alphaL_Kpipi": 0.23984147888569726,
        "alphaR": -1.8978835176522455,
        "alphaR_Kpipi": -3.45169511727099,
        "fraction_Kpipi": 0.8861855867303668,
        "muL_Kpipi": 5214.656416664541,
        "muR_Kpipi": 5183.074248990296,
        "nL": 0.6535660696272864,
        "nL_Kpipi": 4.413073505098077,
        "nR": 2.0973658227474825,
        "nR_Kpipi": 1.3686501931786665e-08,
        "r_bkgK": 0.034754054837981975,
        "sigmaL_Kpipi": 19.133710600596434,
        "sigmaR_Kpipi": 39.32384704379869
    },
    "sigmaL;1330": 11.73889995920766,
    "sigmaL;1330_err": 0.1872911725318502,
    "sigmaR;1330": 19.059279566749968,
    "sigmaR;1330_err": 0.29397890261539267
}